snippy/__init__.py
snippy/__main__.py
snippy/app.py
snippy/interactive_mode.py
snippy_cli-1.0.0.dist-info/METADATA
snippy_cli-1.0.0.dist-info/WHEEL
snippy_cli-1.0.0.dist-info/entry_points.txt
snippy_cli-1.0.0.dist-info/top_level.txt
snippy_cli-1.0.0.dist-info/RECORD
