Metadata-Version: 2.1
Name: snippy-cli
Version: 1.0.0
Summary: A CLI tool for managing code snippets
Home-page: https://github.com/TejasBaid/snippy-cli
Author: Tejas Baid
Author-email: Tejas Baid <tejasbaid3@gmail.com>
Project-URL: homepage, https://github.com/TejasBaid/snippy-cli
Requires-Python: >=3.6
Requires-Dist: pyperclip
Requires-Dist: python-editor
